PyCmdex/__init__.py
PyCmdex/cmdex.py
PyCmdex/cmdex_apis.py
PyCmdex/cmdex_core.py
PyCmdex/cmdex_mcu.py
PyCmdex/cmdex_serial.py
PyCmdex-1.1.19.dist-info/LICENSE
PyCmdex-1.1.19.dist-info/METADATA
PyCmdex-1.1.19.dist-info/WHEEL
PyCmdex-1.1.19.dist-info/entry_points.txt
PyCmdex-1.1.19.dist-info/top_level.txt
PyCmdex-1.1.19.dist-info/RECORD
