Metadata-Version: 2.1
Name: PyCmdex
Version: 1.1.19
Summary: The PyCmdex is a package used to control microcontroller board running the Cmdex firmware.
Home-page: https://github.com/drsanti/PyCmdex
Author: Asst.Prof.Dr.Santi Nuratch
Author-email: santi.inc.kmutt@gmail.com
License: MIT
Platform: UNKNOWN
Classifier: License :: OSI Approved :: MIT License
Classifier: Programming Language :: Python :: 3
Classifier: Programming Language :: Python :: 3.8
Requires-Python: >=3.8
Requires-Dist: pyserial
Requires-Dist: keyboard
